{
    "description": {
        "text": [
            "Selector: .navexDesktopLayoutContainer",
            "Represents the navex:DesktopLayoutContainer component."
        ],
        "author": "Salesforce"
    },
    "root": true,
    "selector": {
        "css": ".navexDesktopLayoutContainer"
    },
    "elements": [
        {
            "name": "appNavPrivate",
            "type": "salesforce-pageobjects/global/pageObjects/appNav",
            "selector": {
                "css": "one-appnav"
            }
        }
    ],
    "methods" : [
        {
            "name" : "getAppNav",
            "compose" : [
                {
                    "apply" : "waitFor",
                    "args" : [
                        {
                            "type" : "function",
                            "predicate" : [
                                {
                                    "element" : "appNavPrivate"
                                }
                            ]
                        }
                    ]
                }
            ]
        }
    ]
}
